kmerexplor/__init__.py
kmerexplor/checkFile.py
kmerexplor/common.py
kmerexplor/config.yaml
kmerexplor/core.py
kmerexplor/countTags
kmerexplor/counts.py
kmerexplor/echarts.common.min.js
kmerexplor/info.py
kmerexplor/mk_results.py
kmerexplor/options.py
kmerexplor/samples.py
kmerexplor/tagsets/human-quality.fa.gz
kmerexplor/tagsets/human-quality.md
kmerexplor/tagsets/human-quality.yaml
kmerexplor-1.1.5.dist-info/licenses/LICENCE.md
kmerexplor-1.1.5.dist-info/METADATA
kmerexplor-1.1.5.dist-info/WHEEL
kmerexplor-1.1.5.dist-info/entry_points.txt
kmerexplor-1.1.5.dist-info/top_level.txt
kmerexplor-1.1.5.dist-info/RECORD
