Metadata-Version: 2.4
Name: kmerexplor
Version: 1.1.5
Summary: KmerExploR provides information on RNA-sequencing datasets.
Home-page: https://github.com/Transipedia/KmerExploR
Author: Benoit Guibert
Author-email: benoit.guibert@free.fr
License: GPLv3
Classifier: Development Status :: 3 - Alpha
Classifier: License :: OSI Approved :: GNU General Public License v3 (GPLv3)
Classifier: Operating System :: POSIX :: Linux
Classifier: Programming Language :: Python
Classifier: Natural Language :: English
Classifier: Intended Audience :: Science/Research
Requires-Python: >=3.6
License-File: LICENCE.md
Requires-Dist: PyYAML
Requires-Dist: markdown
Dynamic: author
Dynamic: author-email
Dynamic: classifier
Dynamic: description
Dynamic: description-content-type
Dynamic: home-page
Dynamic: license
Dynamic: license-file
Dynamic: requires-dist
Dynamic: requires-python
Dynamic: summary
